dao_analyzer-1.3.6-py3.12-nspkg.pth
dao_analyzer/web/__init__.py
dao_analyzer/web/__main__.py
dao_analyzer/web/_version.py
dao_analyzer/web/app.py
dao_analyzer/web/logs.py
dao_analyzer/web/matomo.py
dao_analyzer/web/apps/__init__.py
dao_analyzer/web/apps/aragon/__init__.py
dao_analyzer/web/apps/aragon/business/__init__.py
dao_analyzer/web/apps/aragon/business/app_service.py
dao_analyzer/web/apps/aragon/business/metric_adapter/__init__.py
dao_analyzer/web/apps/aragon/business/metric_adapter/asset_tokens.py
dao_analyzer/web/apps/aragon/business/metric_adapter/asset_values.py
dao_analyzer/web/apps/aragon/business/metric_adapter/basic_adapter.py
dao_analyzer/web/apps/aragon/business/metric_adapter/cast_type.py
dao_analyzer/web/apps/aragon/business/metric_adapter/installed_apps.py
dao_analyzer/web/apps/aragon/business/metric_adapter/vote_outcome.py
dao_analyzer/web/apps/aragon/data_access/__init__.py
dao_analyzer/web/apps/aragon/data_access/daos/__init__.py
dao_analyzer/web/apps/aragon/data_access/daos/platform_dao.py
dao_analyzer/web/apps/aragon/data_access/daos/metric/__init__.py
dao_analyzer/web/apps/aragon/data_access/daos/metric/metric_dao_factory.py
dao_analyzer/web/apps/aragon/data_access/daos/metric/srcs.py
dao_analyzer/web/apps/aragon/data_access/daos/metric/strategy/__init__.py
dao_analyzer/web/apps/aragon/data_access/daos/metric/strategy/st_active_organization.py
dao_analyzer/web/apps/aragon/data_access/daos/metric/strategy/st_active_token_holders.py
dao_analyzer/web/apps/aragon/data_access/daos/metric/strategy/st_active_voters.py
dao_analyzer/web/apps/aragon/data_access/daos/metric/strategy/st_approval_vote_rate.py
dao_analyzer/web/apps/aragon/data_access/daos/metric/strategy/st_assets_tokens.py
dao_analyzer/web/apps/aragon/data_access/daos/metric/strategy/st_assets_values.py
dao_analyzer/web/apps/aragon/data_access/daos/metric/strategy/st_cast_type.py
dao_analyzer/web/apps/aragon/data_access/daos/metric/strategy/st_casted_votes_rate.py
dao_analyzer-1.3.6.dist-info/licenses/LICENSE
dao_analyzer-1.3.6.dist-info/METADATA
dao_analyzer-1.3.6.dist-info/WHEEL
dao_analyzer-1.3.6.dist-info/entry_points.txt
dao_analyzer-1.3.6.dist-info/namespace_packages.txt
dao_analyzer-1.3.6.dist-info/top_level.txt
dao_analyzer-1.3.6.dist-info/RECORD
