Metadata-Version: 2.4
Name: dao-analyzer
Version: 1.3.6
Summary: "A tool to monitor DAO activity"
Home-page: https://dao-analyzer.science
Author: David Davó
Author-email: ddavo@ucm.es
Project-URL: Source, https://github.com/Grasia/dao-analyzer
Project-URL: Bug Tracker, https://github.com/Grasia/dao-analyzer/issues
Project-URL: Changelog, https://github.com/Grasia/dao-analyzer/blob/master/CHANGELOG.md
Classifier: Development Status :: 5 - Production/Stable
Classifier: Environment :: Console
Classifier: Environment :: Web Environment
Classifier: Framework :: Dash
Classifier: Intended Audience :: Science/Research
Classifier: License :: OSI Approved :: GNU General Public License v3 (GPLv3)
Classifier: Programming Language :: Python :: 3
Classifier: Programming Language :: Python :: 3.9
Classifier: Programming Language :: Python :: 3.10
Classifier: Programming Language :: Python :: 3.11
Classifier: Programming Language :: Python :: 3.12
Classifier: Topic :: Scientific/Engineering :: Visualization
Classifier: Topic :: Sociology
Classifier: Typing :: Typed
Classifier: Topic :: Utilities
Requires-Python: >=3.9
License-File: LICENSE
Requires-Dist: dao-scripts==1.5.4
Requires-Dist: dash>=2.17.0
Requires-Dist: dash-bootstrap-components>=1.1.0
Requires-Dist: Werkzeug<2.1.0
Requires-Dist: flask>=2.0.2
Requires-Dist: gql>=3.0.0a1
Requires-Dist: millify>=0.1.1
Requires-Dist: numpy>=1.17.3
Requires-Dist: pandas>=1.3.4
Requires-Dist: portalocker>=2.3.2
Requires-Dist: pyarrow>=6.0.0
Requires-Dist: requests>=2.26.0
Requires-Dist: requests-cache>=0.8.1
Requires-Dist: requests-toolbelt>=0.9.1
Requires-Dist: tenacity>=8.0.0
Requires-Dist: tqdm>=4.62.3
Requires-Dist: plotly-calplot==0.1.13
Provides-Extra: docker
Requires-Dist: gunicorn>=20.1.0; extra == "docker"
Requires-Dist: kaggle>=1.5.12; extra == "docker"
Requires-Dist: zenodo-client>=0.3.0; extra == "docker"
Provides-Extra: dev
Requires-Dist: build; extra == "dev"
Requires-Dist: pytest; extra == "dev"
Requires-Dist: hypothesis; extra == "dev"
Requires-Dist: flake8; extra == "dev"
Requires-Dist: pandas-vet; extra == "dev"
Requires-Dist: twine; extra == "dev"
Requires-Dist: dash[dev,testing]; extra == "dev"
Requires-Dist: pytest; extra == "dev"
Requires-Dist: hypothesis; extra == "dev"
Requires-Dist: pandas-vet; extra == "dev"
Requires-Dist: selenium; extra == "dev"
Dynamic: license-file
